ncollpyde-0.19.0.dist-info/METADATA
ncollpyde-0.19.0.dist-info/WHEEL
ncollpyde/ncollpyde.pyi
ncollpyde/__init__.py
ncollpyde/main.py
ncollpyde/ncollpyde.abi3.so
ncollpyde-0.19.0.dist-info/RECORD
