Metadata-Version: 2.1
Name: ncollpyde
Version: 0.19.0
Classifier: Development Status :: 2 - Pre-Alpha
Classifier: Intended Audience :: Developers
Classifier: License :: OSI Approved :: MIT License
Classifier: Natural Language :: English
Classifier: Programming Language :: Rust
Classifier: Programming Language :: Python :: 3
Classifier: Programming Language :: Python :: 3.7
Classifier: Programming Language :: Python :: 3.8
Classifier: Programming Language :: Python :: 3.9
Requires-Dist: numpy>=1.21.0
Requires-Dist: trimesh[easy]>=3.7.7; extra == 'validate'
Provides-Extra: validate
Summary: A python wrapper around a subset of the ncollide rust library
Author: Chris L. Barnes <chrislloydbarnes@gmail.com>
Author-email: Chris L. Barnes <chrislloydbarnes@gmail.com>
Requires-Python: >=3.6
